reshipe/__init__.py
reshipe/types.py
reshipe/parser/__init__.py
reshipe/parser/recipe.py
reshipe/resource/__init__.py
reshipe-0.1.0.dist-info/METADATA
reshipe-0.1.0.dist-info/WHEEL
reshipe-0.1.0.dist-info/licenses/LICENSE
reshipe-0.1.0.dist-info/RECORD
