Metadata-Version: 2.3
Name: reshipe
Version: 0.1.0
Summary: re(sh)ipe is a versatile Python module designed for efficient data transformation and validation.
Project-URL: Homepage, https://dvm-shlee.github.io
Author-email: SungHo Lee <shlee@unc.edu>
Maintainer-email: SungHo Lee <shlee@unc.edu>
License: MIT
License-File: LICENSE
Keywords: metadata,parser,recipe,reshape,yalm
Classifier: Development Status :: 3 - Alpha
Classifier: Intended Audience :: Developers
Classifier: License :: OSI Approved :: MIT License
Classifier: Programming Language :: Python :: 3
Classifier: Programming Language :: Python :: 3.7
Classifier: Programming Language :: Python :: 3.8
Classifier: Programming Language :: Python :: 3.9
Classifier: Programming Language :: Python :: 3.10
Classifier: Topic :: Software Development :: Libraries :: Python Modules
Requires-Python: >=3.7
Requires-Dist: pyyaml>=6.0.1
Provides-Extra: dev
Requires-Dist: pytest; extra == 'dev'
Requires-Dist: types-pyyaml; extra == 'dev'
